nester_function/__init__.py
tahmimshovon_nester-0.0.4.dist-info/LICENSE.txt
tahmimshovon_nester-0.0.4.dist-info/METADATA
tahmimshovon_nester-0.0.4.dist-info/WHEEL
tahmimshovon_nester-0.0.4.dist-info/top_level.txt
tahmimshovon_nester-0.0.4.dist-info/RECORD
