Metadata-Version: 2.1
Name: tahmimshovon-nester
Version: 0.0.4
Summary: This is a simple function that prints out nested lists
Home-page: UNKNOWN
Author: Tahmim_SHovon
Author-email: tahmim14@gmail.com
License: UNKNOWN
Platform: UNKNOWN
Classifier: Programming Language :: Python :: 3
Classifier: License :: OSI Approved :: MIT License
Classifier: Operating System :: OS Independent
License-File: LICENSE.txt
